{
  "summary": "List the people a user follows",
  "description": "Lists the people who the specified user follows.",
  "tags": [
    "users"
  ],
  "operationId": "users/list-following-for-user",
  "externalDocs": {
    "description": "API method documentation",
    "url": "https://docs.github.com/rest/users/followers#list-the-people-a-user-follows"
  },
  "parameters": [
    {
      "$ref": "#/components/parameters/username"
    },
    {
      "$ref": "#/components/parameters/per-page"
    },
    {
      "$ref": "#/components/parameters/page"
    }
  ],
  "responses": {
    "200": {
      "description": "Response",
      "content": {
        "application/json": {
          "schema": {
            "type": "array",
            "items": {
              "$ref": "#/components/schemas/simple-user"
            }
          },
          "examples": {
            "default": {
              "$ref": "#/components/examples/simple-user-items"
            }
          }
        }
      },
      "headers": {
        "Link": {
          "$ref": "#/components/headers/link"
        }
      }
    }
  },
  "x-github": {
    "githubCloudOnly": false,
    "enabledForGitHubApps": true,
    "category": "users",
    "subcategory": "followers"
  }
}
