{
  "summary": "Get default workflow permissions for a repository",
  "description": "Gets the default workflow permissions granted to the `GITHUB_TOKEN` when running workflows in a repository,\nas well as if GitHub Actions can submit approving pull request reviews.\nFor more information, see \"[Setting the permissions of the GITHUB_TOKEN for your repository](https://docs.github.com/repositories/managing-your-repositorys-settings-and-features/enabling-features-for-your-repository/managing-github-actions-settings-for-a-repository#setting-the-permissions-of-the-github_token-for-your-repository).\"\n\nOAuth tokens and personal access tokens (classic) need the `repo` scope to use this endpoint.",
  "tags": [
    "actions"
  ],
  "operationId": "actions/get-github-actions-default-workflow-permissions-repository",
  "externalDocs": {
    "description": "API method documentation",
    "url": "https://docs.github.com/rest/actions/permissions#get-default-workflow-permissions-for-a-repository"
  },
  "parameters": [
    {
      "$ref": "#/components/parameters/owner"
    },
    {
      "$ref": "#/components/parameters/repo"
    }
  ],
  "responses": {
    "200": {
      "description": "Response",
      "content": {
        "application/json": {
          "schema": {
            "$ref": "#/components/schemas/actions-get-default-workflow-permissions"
          },
          "examples": {
            "default": {
              "$ref": "#/components/examples/actions-default-workflow-permissions"
            }
          }
        }
      }
    }
  },
  "x-github": {
    "githubCloudOnly": false,
    "enabledForGitHubApps": true,
    "category": "actions",
    "subcategory": "permissions"
  }
}
