{
  "summary": "Get self-hosted runners settings for an organization",
  "description": "Gets the settings for self-hosted runners for an organization.\n\nOAuth app tokens and personal access tokens (classic) need the `admin:org` scope or the \"Actions policies\" fine-grained permission to use this endpoint.",
  "operationId": "actions/get-self-hosted-runners-permissions-organization",
  "tags": [
    "actions"
  ],
  "externalDocs": {
    "description": "API method documentation",
    "url": "https://docs.github.com/rest/actions/permissions#get-self-hosted-runners-settings-for-an-organization"
  },
  "parameters": [
    {
      "$ref": "#/components/parameters/org"
    }
  ],
  "responses": {
    "200": {
      "description": "Response",
      "content": {
        "application/json": {
          "schema": {
            "$ref": "#/components/schemas/self-hosted-runners-settings"
          },
          "examples": {
            "response": {
              "summary": "Example response",
              "value": {
                "enabled_repositories": "selected",
                "selected_repositories_url": "http://api.github.localhost/organizations/1/actions/permissions/self-hosted-runners/repositories"
              }
            }
          }
        }
      }
    },
    "403": {
      "$ref": "#/components/responses/forbidden"
    },
    "404": {
      "$ref": "#/components/responses/not_found"
    }
  },
  "x-github": {
    "enabledForGitHubApps": true,
    "category": "actions",
    "subcategory": "permissions"
  }
}
